vise/__init__.py
vise/defaults.py
vise/error.py
vise/tmp.py
vise/user_settings.py
vise/version.py
vise/analyzer/__init__.py
vise/analyzer/atom_grouping_type.py
vise/analyzer/band_edge_properties.py
vise/analyzer/dielectric_function.py
vise/analyzer/dos_data.py
vise/analyzer/effective_mass.py
vise/analyzer/plot_band.py
vise/analyzer/plot_brillouin_zone.py
vise/analyzer/plot_diele_func_data.py
vise/analyzer/plot_dos.py
vise/analyzer/dielectric_function_data/GaAs.csv
vise/analyzer/dielectric_function_data/Si.csv
vise/analyzer/dielectric_function_data/exp_dielectric_func.py
vise/analyzer/vasp/__init__.py
vise/analyzer/vasp/band_edge_properties.py
vise/analyzer/vasp/dos_data.py
vise/analyzer/vasp/handle_volumetric_data.py
vise/analyzer/vasp/make_diele_func.py
vise/analyzer/vasp/make_effective_mass.py
vise/analyzer/vasp/make_irreps.py
vise/analyzer/vasp/plot_band.py
vise/analyzer/vesta/__init__.py
vise/analyzer/vesta/element_colors.py
vise/analyzer/vesta/vesta_file.py
vise/atom_energies/__init__.py
vise/atom_energies/atom_energy.py
vise/atom_energies/atom_magnetization_hund.yaml
vise/atom_energies/get_energy.py
vise/atom_energies/make_atom_vasp_set.py
vise/atom_energies/mp_atom_energy.yaml
vise/atom_energies/mp_atom_mag.yaml
vise/cli/__init__.py
vise/cli/main.py
vise/cli/main_functions.py
vise/cli/main_tools.py
vise/cli/main_util.py
vise/cli/main_util_functions.py
vise/input_set/__init__.py
vise/input_set/fft_grids.py
vise/input_set/incar.py
vise/input_set/incar_settings_generator.py
vise/input_set/input_options.py
vise/input_set/kpoints.py
vise/input_set/kpoints_mode.py
vise/input_set/potcar_generator.py
vise/input_set/prior_info.py
vise/input_set/structure_kpoints_generator.py
vise/input_set/task.py
vise/input_set/vasp_input_files.py
vise/input_set/vise_log.py
vise/input_set/xc.py
vise/input_set/datasets/__init__.py
vise/input_set/datasets/dataset_util.py
vise/input_set/datasets/incar_flags.yaml
vise/input_set/datasets/kpar_set.yaml
vise/input_set/datasets/magmom.yaml
vise-0.9.5.dist-info/LICENSE
vise-0.9.5.dist-info/METADATA
vise-0.9.5.dist-info/WHEEL
vise-0.9.5.dist-info/entry_points.txt
vise-0.9.5.dist-info/top_level.txt
vise-0.9.5.dist-info/RECORD
