Metadata-Version: 2.1
Name: vise
Version: 0.9.5
Summary: Package for handling io of vasp package in kumagai group at IMR, Tohoku university
Home-page: https://github.com/kumagai-group/vise
Author: Yu Kumagai
Author-email: yukumagai@tohoku.ac.jp
License: MIT license
Platform: UNKNOWN
Classifier: Programming Language :: Python :: 3.7
Classifier: License :: OSI Approved :: MIT License
Requires-Python: >=3.7
Requires-Dist: pymatgen
Requires-Dist: seekpath
Requires-Dist: num2words
Requires-Dist: more-itertools
Requires-Dist: phonopy
Requires-Dist: mp-api
